{
  "selectedTemplate": 1,
  "headings": {
    "work": "Work Experience",
    "education": "Education",
    "skills": "Skills",
    "projects": "Projects"
  },
  "basics": {
    "name": "Alex Goldsmith",
    "email": "gold.alex.smith@gmail.com",
    "phone": "608-622-7567",
    "location": {
      "address": "Madison, Wisconsin"
    }
  },
  "education": [
    {
      "institution": "University of Wisconsin - Madison",
      "location": "Madison, Wisconsin",
      "startDate": "Dec 2020",
      "endDate": "August 2022",
      "studyType": "Coursework in Computer Science"
    },
    {
      "institution": "Clemson University",
      "location": "Clemson, South Carolina",
      "studyType": "MA",
      "area": "Economics",
      "startDate": "Aug 2018",
      "endDate": "Aug 2019"
    },
    {
      "institution": "Clemson University",
      "location": "Clemson, South Carolina",
      "studyType": "BA",
      "area": "Economics",
      "startDate": "Aug 2015",
      "endDate": "May 2018"
    }
  ],
  "work": [
    {
      "position": "Technical Solutions Engineer",
      "company": "SpectrumAi",
      "location": "Madison, Wisconsin",
      "startDate": "Jan 2023",
      "endDate": "June 2023",
      "highlights": [
        "Brought the company's first customer live within a week of hiring.",
        "Owned and resolved customer issues from first contact through to code deployment."
      ]
    },
    {
      "company": "Epic Systems Corporation",
      "position": "Technical Solutions Engineer",
      "location": "Madison, Wisconsin",
      "startDate": "Dec 2019",
      "endDate": "Jun 2021",
      "highlights": [
        "Ensured continued success of 6 hospital system organizations live on Epic’s registration and real-time eligibility applications through dozens of major software upgrades.",
        "Consistently maintained a success rate (greater than 90%) for First Response Time targets within the top half of the application support team.",
        "Investigated technical bugs encountered by customers via methods such as code walkthroughs, application testing, and code debugging. Achieved customer-accepted resolution of 100% of submitted issues.",
        "Owned high-impact customer issues from discovery to resolution, including issues within other Epic applications.",
        "Documented customer requirements, technical bugs and broken workflows, application functionality, and user feedback.",
        "Provided technical expertise to a customer implementation project, while mentoring the customer’s long-term support engineer."
      ]
    },
    {
      "highlights": [""]
    }
  ],
  "skills": [
    {
      "name": "Programming Languages",
      "level": "",
      "keywords": ["Python, TypeScript, JavaScript, C++, Java, MUMPS"]
    },
    {
      "keywords": ["React, React-Native, Svelte, Astro, Remix"],
      "name": "Front-end Frameworks"
    },
    {
      "keywords": [
        "SQL, PostgresSQL, MySQL, MongoDB, Firebase, Relational & Document Models"
      ],
      "name": "Database Technologies"
    },
    {
      "keywords": ["Google Cloud Platform (GCP), Microsoft Azure"],
      "name": "Cloud Platforms"
    },
    {
      "keywords": [
        "NodeJS, Jest, Git, Docker, CMake, JSON, HTML, CSS, REST APIs, X12, LaTeX"
      ],
      "name": "Other Technologies"
    },
    {
      "keywords": [
        "Competent and flexible team-leadership using considered emotional intelligence"
      ],
      "name": "Leadership"
    },
    {
      "keywords": ["Capable task and time management"],
      "name": "Organization"
    },
    {
      "keywords": [
        "Skilled written and interpersonal communication across multiple modalities"
      ],
      "name": "Communication"
    },
    {
      "keywords": [
        "Adept innovative and entreprenurial skills combined with problem-solving acumen"
      ],
      "name": "Creativity"
    }
  ],
  "projects": [
    {
      "name": "ActivityPub Server",
      "keywords": ["Nodejs, Qwik"],
      "description": "Web server implementing ActivityPub and Mastodon protocols as well as web client built with Qwik"
    },
    {
      "name": "Badger Mental Health",
      "keywords": ["React-Native, Expo, Jest, Google Firebase"],
      "description": "Participated in a team of 3 developers to create a web and mobile application with create/read/update/delete functionality for a course project. Stack included React front-end and NodeJs backend connecting to a document based database.",
      "url": "https://github.com/alexgoldsmith/badgermentalhealth"
    },
    {
      "keywords": ["JavaScript, PyScript, Python, SQLite"],
      "name": "Stack Overflow Survey Visualization",
      "description": "Created a web application for a course project using PyScript, JavaScript, and SQLite. The Web application allowed users to query a database, and subsequently displayed a visualization."
    }
  ],
  "awards": [
    {
      "title": "",
      "date": "",
      "awarder": "",
      "summary": ""
    }
  ],
  "sections": [
    "templates",
    "profile",
    "work",
    "education",
    "projects",
    "skills",
    "awards"
  ]
}
